akamai_network_lists/network_lists_api_wrapper.py
akamai_network_lists-0.0.4.dist-info/METADATA
akamai_network_lists-0.0.4.dist-info/WHEEL
akamai_network_lists-0.0.4.dist-info/licenses/LICENSE
akamai_network_lists-0.0.4.dist-info/RECORD
